{
  "promotions": [
    {
      "title": "Dreamgear Dgps3-3881 Controle Shadow Pro Wireless 2.4ghz - Android",
      "url": "https://amzn.to/3CzyYXl",
      "imageUrl": "https://cdn.gatry.com/gatry-static/promocao/imagem/585f08d7ff6d1ed815c6a8c8ac2685af.jpg",
      "price": 204.01,
      "id": 5
    },
    {
      "title": "Notebook Legacy Cloud 2GB 64GB Winows 10 Home Multilaser Vermelho - PC135",
      "url": "https://amzn.to/3mcAiK1",
      "imageUrl": "https://cdn.gatry.com/gatry-static/promocao/imagem/db208109dd1f5ec06ba3ab94d005aa80.jpg",
      "price": 1.235,
      "id": 1
    },
    {
      "title": "TV LG 50'' UHD 4k 50US660H0SD IPS Com Hotel Procentric",
      "url": "https://produto.mercadolivre.com.br/MLB-1871575258-tv-lg-50-uhd-4k-50us660h0sd-ips-com-hotel-procentric-_JM",
      "imageUrl": "https://cdn.gatry.com/gatry-static/promocao/imagem/28a5ed90a4ec85710f8ba4d27d1ac0b6.jpg",
      "price": 1.799,
      "id": 6
    },
    {
      "title": "Computador Desktop Completo com Monitor 19.5\" HDMI Intel Core i3 4GB HD 500GB",
      "url": "https://amzn.to/3GziG33",
      "imageUrl": "https://cdn.gatry.com/gatry-static/promocao/imagem/8b04947f5578268e81f0f015aa5c8620.jpg",
      "price": 1.623,
      "id": 7
    }
  ],
  "comments": [
    {
      "id": 1,
      "comment": "TELA HD",
      "promotionId": 1
    },
    {
      "id": 2,
      "comment": "de R$ 599,90 \n por R$246,05à vista \n (5% de desconto) \n ou R$ 259,00 em 5x de R$ 51,80 sem juros",
      "promotionId": 2
    }
  ]
}